algobase/__init__.py
algobase/algorand/__init__.py
algobase/algorand/account.py
algobase/algorand/client.py
algobase/algorand/dispenser.py
algobase/algorand/simple_mint.py
algobase/choices.py
algobase/data/__init__.py
algobase/data/ipfs.toml
algobase/functional.py
algobase/ipfs/__init__.py
algobase/ipfs/client_base.py
algobase/ipfs/nft_storage.py
algobase/models/__init__.py
algobase/models/algod.py
algobase/models/arc19.py
algobase/models/arc3.py
algobase/models/asa.py
algobase/models/asset_params.py
algobase/models/dispenser.py
algobase/models/kmd.py
algobase/settings.py
algobase/types/__init__.py
algobase/types/annotated.py
algobase/utils/__init__.py
algobase/utils/cid.py
algobase/utils/hash.py
algobase/utils/read.py
algobase/utils/url.py
algobase/utils/validate.py
algobase-0.12.8.dist-info/LICENSE
algobase-0.12.8.dist-info/METADATA
algobase-0.12.8.dist-info/WHEEL
algobase-0.12.8.dist-info/entry_points.txt
algobase-0.12.8.dist-info/RECORD
