Metadata-Version: 2.1
Name: algobase
Version: 0.12.8
Summary: A type-safe Python library for interacting with assets on Algorand.
Home-page: https://github.com/code-alexander/algobase
License: Apache Software License 2.0
Author: algobase
Author-email: alexandercodes@proton.me
Requires-Python: >=3.11,<4.0
Classifier: Development Status :: 3 - Alpha
Classifier: Intended Audience :: Developers
Classifier: License :: OSI Approved :: Apache Software License
Classifier: License :: Other/Proprietary License
Classifier: Operating System :: OS Independent
Classifier: Programming Language :: Python :: 3
Classifier: Programming Language :: Python :: 3.11
Classifier: Programming Language :: Python :: 3.12
Classifier: Topic :: Software Development :: Libraries :: Python Modules
Requires-Dist: babel (>=2.14.0,<3.0.0)
Requires-Dist: cytoolz (>=0.12.2,<0.13.0)
Requires-Dist: fastapi (>=0.109,<0.111)
Requires-Dist: httpx (>=0.23.1,<0.24.0)
Requires-Dist: mypy (>=1.10.1,<2.0.0)
Requires-Dist: py-algorand-sdk (>=2.5.0,<3.0.0)
Requires-Dist: py-multiformats-cid (>=0.4.4,<0.5.0)
Requires-Dist: pydantic (>=2.5.3,<3.0.0)
Requires-Dist: pydantic-settings (>=2.1.0,<3.0.0)
Requires-Dist: pytest-httpx (>=0.21.3,<0.22.0)
Requires-Dist: returns (>=0.22.0,<0.23.0)
Requires-Dist: rich (>=13.7.0,<14.0.0)
Requires-Dist: typer[all] (>=0.9,<0.13)
Project-URL: Repository, https://github.com/code-alexander/algobase
